AuthNex/Adventure.py
AuthNex/DailyWeeklyMonthly.py
AuthNex/Database.py
AuthNex/Msg.py
AuthNex/Shop.py
AuthNex/__init__.py
AuthNex/__main__.py
AuthNex/accounts.py
AuthNex/broadcast.py
AuthNex/change.py
AuthNex/items.py
AuthNex/login.py
AuthNex/logout.py
AuthNex/my_info.py
AuthNex/pay.py
AuthNex/profile.py
AuthNex/refer.py
AuthNex/register.py
AuthNex/report.py
AuthNex/reset.py
AuthNex/start.py
AuthNex/system.py
AuthNex/token_generator.py
AuthNex/tournament.py
AuthNex/Modules/__init__.py
AuthNex/Modules/auth.py
authnex-1.1.dist-info/licenses/LICENSE
authnex-1.1.dist-info/METADATA
authnex-1.1.dist-info/WHEEL
authnex-1.1.dist-info/top_level.txt
authnex-1.1.dist-info/RECORD
