Metadata-Version: 2.4
Name: AuthNex
Version: 1.1
Summary: just a try
Home-page: https://github.com/RyomenSukuna53/AuthNex
Author: Kuro__
Author-email: sufyan532011@gmail.com
Classifier: Programming Language :: Python :: 3
Classifier: License :: OSI Approved :: MIT License
Classifier: Operating System :: OS Independent
Requires-Python: >=3.10
License-File: LICENSE
Requires-Dist: pyrogram
Requires-Dist: tgcrypto
Requires-Dist: pymongo
Requires-Dist: dnspython
Dynamic: author
Dynamic: author-email
Dynamic: classifier
Dynamic: description
Dynamic: description-content-type
Dynamic: home-page
Dynamic: license-file
Dynamic: requires-dist
Dynamic: requires-python
Dynamic: summary
